djangoctl/__init__.py
djangoctl/_nbdev.py
djangoctl/core.py
djangoctl-0.0.2.dist-info/LICENSE
djangoctl-0.0.2.dist-info/METADATA
djangoctl-0.0.2.dist-info/WHEEL
djangoctl-0.0.2.dist-info/entry_points.txt
djangoctl-0.0.2.dist-info/top_level.txt
djangoctl-0.0.2.dist-info/RECORD
