Metadata-Version: 2.1
Name: djangoctl
Version: 0.0.2
Summary: An alt Django Command Line Tool
Home-page: https://github.com/codingforentrepreneurs/djangoctl/tree/main/
Author: Justin Mitchel
Author-email: hello@teamcfe.com
License: Apache Software License 2.0
Keywords: django,command line
Platform: UNKNOWN
Classifier: Development Status :: 3 - Alpha
Classifier: Intended Audience :: Developers
Classifier: Natural Language :: English
Classifier: Programming Language :: Python :: 3.7
Classifier: Programming Language :: Python :: 3.8
Classifier: Programming Language :: Python :: 3.9
Classifier: Programming Language :: Python :: 3.10
Classifier: License :: OSI Approved :: Apache Software License
Requires-Python: >=3.7
Requires-Dist: pip
Requires-Dist: packaging
Requires-Dist: cryptography
Requires-Dist: fire
Requires-Dist: requests
Requires-Dist: rich
Provides-Extra: dev
